cymem/__init__.py
cymem/__init__.pxd
cymem/cymem.pxd
cymem/cymem.pyx
cymem/cymem.cpython-39-x86_64-linux-gnu.so
cymem/about.py
cymem/tests/test_import.py
cymem/tests/__init__.py
cymem-2.0.8.dist-info/RECORD
cymem-2.0.8.dist-info/WHEEL
cymem-2.0.8.dist-info/METADATA
cymem-2.0.8.dist-info/top_level.txt
cymem-2.0.8.dist-info/LICENSE
